archipelagos/__init__.py
archipelagos/message_aggregator.py
archipelagos/message_storer.py
archipelagos/common/__init__.py
archipelagos/common/platform.py
archipelagos/common/settings.py
archipelagos/common/data/__init__.py
archipelagos/common/data/collection.py
archipelagos/common/data/filestore.py
archipelagos/common/data/filter.py
archipelagos/common/data/timeseries.py
archipelagos/common/protobuf/__init__.py
archipelagos/common/protobuf/common/Timestamp_pb2.py
archipelagos/common/protobuf/common/__init__.py
archipelagos/common/protobuf/common/data/AtomicValue_pb2.py
archipelagos/common/protobuf/common/data/DataEntry_pb2.py
archipelagos/common/protobuf/common/data/DataId_pb2.py
archipelagos/common/protobuf/common/data/__init__.py
archipelagos/common/protobuf/common/data/collection/CollectionData_pb2.py
archipelagos/common/protobuf/common/data/collection/CollectionMetadataRequest_pb2.py
archipelagos/common/protobuf/common/data/collection/CollectionMetadataResponse_pb2.py
archipelagos/common/protobuf/common/data/collection/CollectionMetadata_pb2.py
archipelagos/common/protobuf/common/data/collection/CollectionRequest_pb2.py
archipelagos/common/protobuf/common/data/collection/CollectionResponse_pb2.py
archipelagos/common/protobuf/common/data/collection/Collection_pb2.py
archipelagos/common/protobuf/common/data/filestore/FileMetadataRequest_pb2.py
archipelagos/common/protobuf/common/data/filestore/FileMetadataResponse_pb2.py
archipelagos/common/protobuf/common/data/filestore/FileMetadata_pb2.py
archipelagos/common/protobuf/common/data/filestore/FileStoreMetadataRequest_pb2.py
archipelagos/common/protobuf/common/data/filestore/FileStoreMetadataResponse_pb2.py
archipelagos/common/protobuf/common/data/filestore/FileStoreMetadata_pb2.py
archipelagos/common/protobuf/common/data/filestore/FileStoreRequest_pb2.py
archipelagos/common/protobuf/common/data/filestore/FileStoreResponse_pb2.py
archipelagos/common/protobuf/common/data/timeseries/TimeSeriesData_pb2.py
archipelagos-0.0.23.dist-info/METADATA
archipelagos-0.0.23.dist-info/WHEEL
archipelagos-0.0.23.dist-info/top_level.txt
archipelagos-0.0.23.dist-info/RECORD
