Metadata-Version: 2.1
Name: archipelagos
Version: 0.0.23
Summary: The Python Client for the Archipelagos platform.
Home-page: https://www.archipelagos-labs.com
Author: Archipelagos Labs
Author-email: support@archipelagos-labs.com
License: Apache License, Version 2.0
Classifier: Programming Language :: Python :: 3
Classifier: Programming Language :: Python :: 3.7
Classifier: Programming Language :: Python :: 3.8
Classifier: Programming Language :: Python :: 3.9
Classifier: Programming Language :: Python :: 3.10
Requires-Dist: numpy (>=1.21.2)
Requires-Dist: pandas (>=1.3.5)
Requires-Dist: protobuf (>=3.19.1)
Requires-Dist: requests (>=2.27.1)
Provides-Extra: all
Requires-Dist: geopandas (>=0.10.2) ; extra == 'all'
